asys/__init__.py
asys/agent.py
asys-0.1.0.dist-info/METADATA
asys-0.1.0.dist-info/WHEEL
asys-0.1.0.dist-info/top_level.txt
asys-0.1.0.dist-info/RECORD
