Metadata-Version: 2.4
Name: asys
Version: 0.1.0
Summary: A Python SDK for interacting with the Claude CLI tool
Home-page: https://github.com/asys/asys-sdk
Author: asys
Author-email: asys <info@asys.org>
License: MIT
Project-URL: Homepage, https://github.com/asys/asys-sdk
Project-URL: Bug Tracker, https://github.com/asys/asys-sdk/issues
Keywords: claude,ai,language model,cli,sdk
Classifier: Programming Language :: Python :: 3
Classifier: Programming Language :: Python :: 3.8
Classifier: Programming Language :: Python :: 3.9
Classifier: Programming Language :: Python :: 3.10
Classifier: License :: OSI Approved :: MIT License
Classifier: Operating System :: OS Independent
Classifier: Development Status :: 3 - Alpha
Requires-Python: >=3.8
Dynamic: author
Dynamic: home-page
Dynamic: requires-python
